compress_json/__init__.py
compress_json/__main__.py
compress_json/cli.py
compress_json/config.py
compress_json/core.py
compress_json/core_test.py
compress_json/encode.py
compress_json/helpers.py
compress_json/helpers_test.py
compress_json/memory.py
compress_json/number.py
compress_json/number_test.py
compress_json/type.py
compress_json_python-3.1.2.dist-info/licenses/LICENSE
compress_json_python-3.1.2.dist-info/METADATA
compress_json_python-3.1.2.dist-info/WHEEL
compress_json_python-3.1.2.dist-info/entry_points.txt
compress_json_python-3.1.2.dist-info/top_level.txt
compress_json_python-3.1.2.dist-info/RECORD
