Metadata-Version: 2.4
Name: compress-json-python
Version: 3.1.2
Summary: convert JSON data to space efficient format
Author-email: Beeno Tung <aabbcc1241@yahoo.com.hk>
License: BSD 2-Clause License
Project-URL: Homepage, https://github.com/beenotung/compress-json
Keywords: json,compress
Classifier: License :: OSI Approved :: BSD License
Classifier: Programming Language :: Python
Classifier: Programming Language :: Python :: 3
License-File: LICENSE
Dynamic: license-file
